tom_alerts/__init__.py
tom_alerts/admin.py
tom_alerts/alerts.py
tom_alerts/apps.py
tom_alerts/brokers/__init__.py
tom_alerts/brokers/alerce.py
tom_alerts/brokers/antares.py
tom_alerts/brokers/fink.py
tom_alerts/brokers/gaia.py
tom_alerts/brokers/hermes.py
tom_alerts/brokers/lasair.py
tom_alerts/brokers/scout.py
tom_alerts/brokers/tns.py
tom_alerts/exceptions.py
tom_alerts/management/__init__.py
tom_alerts/management/commands/__init__.py
tom_alerts/management/commands/runbrokerquery.py
tom_alerts/migrations/0001_initial.py
tom_alerts/migrations/0002_auto_20190626_2135.py
tom_alerts/migrations/0003_auto_20190701_2226.py
tom_alerts/migrations/0004_auto_20210204_2300.py
tom_alerts/migrations/0005_alertstreammessage.py
tom_alerts/migrations/0006_alter_alertstreammessage_exchange_status.py
tom_alerts/migrations/0007_alter_alertstreammessage_message_id.py
tom_alerts/migrations/__init__.py
tom_alerts/models.py
tom_alerts/templates/tom_alerts/brokerquery_confirm_delete.html
tom_alerts/templates/tom_alerts/brokerquery_list.html
tom_alerts/templates/tom_alerts/partials/navbar_link.html
tom_alerts/templates/tom_alerts/partials/submit_upstream_form.html
tom_alerts/templates/tom_alerts/query_form.html
tom_alerts/templates/tom_alerts/query_result.html
tom_alerts/templatetags/alerts_extras.py
tom_alerts/tests/__init__.py
tom_alerts/tests/brokers/__init__.py
tom_alerts/tests/brokers/test_alerce.py
tom_alerts/tests/brokers/test_gaia.py
tom_alerts/tests/brokers/test_lasair.py
tom_alerts/tests/tests.py
tom_alerts/urls.py
tom_alerts/views.py
tom_base/__init__.py
tom_base/settings.py
tom_base/wsgi.py
tom_catalogs/__init__.py
tom_catalogs/admin.py
tom_catalogs/apps.py
tom_catalogs/forms.py
tom_catalogs/harvester.py
tom_catalogs/harvesters/__init__.py
tom_catalogs/harvesters/jplhorizons.py
tom_catalogs/harvesters/mpc.py
tom_catalogs/harvesters/ned.py
tom_catalogs/harvesters/simbad.py
tom_catalogs/harvesters/tns.py
tom_catalogs/templates/tom_catalogs/partials/catalog_query_menu.html
tomtoolkit-2.30.1.dist-info/METADATA
tomtoolkit-2.30.1.dist-info/WHEEL
tomtoolkit-2.30.1.dist-info/licenses/LICENSE
tomtoolkit-2.30.1.dist-info/RECORD
