Metadata-Version: 2.4
Name: tomtoolkit
Version: 2.30.1
Summary: TOM Toolkit and base modules
License-Expression: GPL-3.0-only
License-File: LICENSE
Keywords: tomtoolkit,TOM,astronomy,astrophysics,cosmology,science,fits,observatory
Author: TOM Toolkit Project
Author-email: tomtoolkit-maintainers@lco.global
Maintainer: Joey Chatelain
Maintainer-email: jchate6@gmail.com
Requires-Python: >=3.10.0,<3.14
Classifier: Development Status :: 3 - Alpha
Classifier: Intended Audience :: Science/Research
Classifier: License :: OSI Approved :: BSD License
Classifier: Operating System :: OS Independent
Classifier: Programming Language :: Python :: 3
Classifier: Programming Language :: Python :: 3.8
Classifier: Programming Language :: Python :: 3.9
Classifier: Programming Language :: Python :: 3.10
Classifier: Programming Language :: Python :: 3.11
Classifier: Programming Language :: Python :: 3.12
Classifier: Topic :: Scientific/Engineering :: Astronomy
Classifier: Topic :: Scientific/Engineering :: Physics
Requires-Dist: astroplan (>=0.8,<0.11)
Requires-Dist: astropy (>=5.3.3,<6) ; python_version < "3.10"
Requires-Dist: astropy (>=5.3.3,<7) ; python_version >= "3.10"
Requires-Dist: astroquery (<1)
Requires-Dist: beautifulsoup4 (<5)
Requires-Dist: crispy-bootstrap4 (>=2023.1,<2024.11)
Requires-Dist: cryptography (<=46)
Requires-Dist: django (<5)
Requires-Dist: django-bootstrap4 (>3,<25)
Requires-Dist: django-contrib-comments (>=2.0,<3.0)
Requires-Dist: django-crispy-forms (>=2.0,<3.0)
Requires-Dist: django-extensions (>=3.0.0,<4.0.0)
Requires-Dist: django-filter (>=23,<25)
Requires-Dist: django-gravatar2 (>=1.0.0,<2.0.0)
Requires-Dist: django-guardian (>=2.0.0,<3.0.0)
Requires-Dist: django-htmx (>=1.0.0,<2.0.0)
Requires-Dist: django-tasks (>=0.6.1,<0.7.0)
Requires-Dist: djangorestframework (>=3.15,<4)
Requires-Dist: fits2image (>=0.4,<0.5)
Requires-Dist: importlib-resources (>=6.4.5,<6.5.0)
Requires-Dist: markdown (<4)
Requires-Dist: numpy (>1.24,<2.2)
Requires-Dist: pillow (>9.2,<12.0)
Requires-Dist: plotly (<6)
Requires-Dist: python-dateutil (<3)
Requires-Dist: requests (<3)
Requires-Dist: specutils (<2)
